pascal_voc_toolkit/__init__.py
pascal_voc_toolkit/image_handler.py
pascal_voc_toolkit/pascal_voc_dataset.py
pascal_voc_toolkit/pascal_voc_dataset_instance.py
pascal_voc_toolkit/xml_handler.py
tests/__init__.py
tests/test_xml_handler.py
pascal_voc_toolkit-1.0.2.dist-info/METADATA
pascal_voc_toolkit-1.0.2.dist-info/WHEEL
pascal_voc_toolkit-1.0.2.dist-info/top_level.txt
pascal_voc_toolkit-1.0.2.dist-info/RECORD
