Metadata-Version: 2.1
Name: pascal-voc-toolkit
Version: 1.0.2
Summary: Set of tools to work with Pascal VOC annotation format
Home-page: 
Author: Aman Khatri
Author-email: amankhatri.ai@gmail.com
Requires-Dist: dict2xml (==1.7.2)
Requires-Dist: xmltodict (==0.13.0)
Requires-Dist: pytest (==7.2.1)
Requires-Dist: opencv-python (==4.7.0.68)
